ansible_runner_beats/__init__.py
ansible_runner_beats/events.py
ansible_runner_beats-1.0.4.dist-info/LICENSE
ansible_runner_beats-1.0.4.dist-info/METADATA
ansible_runner_beats-1.0.4.dist-info/WHEEL
ansible_runner_beats-1.0.4.dist-info/entry_points.txt
ansible_runner_beats-1.0.4.dist-info/top_level.txt
ansible_runner_beats-1.0.4.dist-info/RECORD
