Metadata-Version: 2.1
Name: ansible-runner-beats
Version: 1.0.4
Home-page: https://github.com/claranet/ansible-runner-beats
Author: Claranet
License: MPL2
License-File: LICENSE
Requires-Dist: pylogbeat
Requires-Dist: deepmerge
